odoo/addons/delivery_roulier_option/README.rst
odoo/addons/delivery_roulier_option/__init__.py
odoo/addons/delivery_roulier_option/__manifest__.py
odoo/addons/delivery_roulier_option/data/delivery.xml
odoo/addons/delivery_roulier_option/i18n/delivery_roulier_option.pot
odoo/addons/delivery_roulier_option/i18n/es.po
odoo/addons/delivery_roulier_option/i18n/fr.po
odoo/addons/delivery_roulier_option/i18n/it.po
odoo/addons/delivery_roulier_option/models/__init__.py
odoo/addons/delivery_roulier_option/models/delivery_option.py
odoo/addons/delivery_roulier_option/models/stock_picking.py
odoo/addons/delivery_roulier_option/models/stock_quant_package.py
odoo/addons/delivery_roulier_option/readme/CONTRIBUTORS.md
odoo/addons/delivery_roulier_option/readme/DESCRIPTION.md
odoo/addons/delivery_roulier_option/static/description/icon.png
odoo/addons/delivery_roulier_option/static/description/index.html
odoo_addon_delivery_roulier_option-17.0.1.0.0.6.dist-info/METADATA
odoo_addon_delivery_roulier_option-17.0.1.0.0.6.dist-info/WHEEL
odoo_addon_delivery_roulier_option-17.0.1.0.0.6.dist-info/top_level.txt
odoo_addon_delivery_roulier_option-17.0.1.0.0.6.dist-info/RECORD
